anymarket/__init__.py
anymarket/anymarketPedidos.py
Anymarket-0.0.5.dist-info/LICENSE
Anymarket-0.0.5.dist-info/METADATA
Anymarket-0.0.5.dist-info/WHEEL
Anymarket-0.0.5.dist-info/top_level.txt
Anymarket-0.0.5.dist-info/RECORD
