Metadata-Version: 2.1
Name: Anymarket
Version: 0.0.5
Summary: Anymarket API
Author: Pablo Belmiro
Author-email: dev.pablobelmiro@gmail.com
Keywords: python,API,Anymarket,Ecommerce
License-File: LICENSE
Requires-Dist: httpx
